{
  "@id": "https://data.datatourisme.fr/13/422b8cbd-d07b-3499-aeac-d7c2a38229e0",
  "dc:identifier": "5238723",
  "@type": [
    "schema:FoodEstablishment",
    "FoodEstablishment",
    "PlaceOfInterest",
    "PointOfInterest"
  ],
  "rdfs:comment": {
    "de": [
      "Im Herzen des Ospedale-Waldes bietet das Refuge seit 1986 seine korsischen Spezialitäten an."
    ],
    "en": [
      "In the heart of the Ospedale forest, the Refuge has been offering its Corsican specialities since 1986."
    ],
    "it": [
      "Nel cuore della foresta dell'Ospedale, il Rifugio offre dal 1986 le sue specialità corse."
    ],
    "fr": [
      "Le Refuge vous propose ses spécialités corses depuis 1986. Ouvert tous les jours, midi et soir. Soirées chants et guitares corses tous les mardis et vendredis en haute saison. Boutique de produits corses. Gîte d'étape du Mare à Mare."
    ],
    "es": [
      "Le Refuge sirve especialidades corsas desde 1986. Abierto todos los días para almorzar y cenar. Veladas de canto y guitarra corsos todos los martes y viernes en temporada alta. Tienda de productos corsos. Gîte d'étape du Mare à Mare."
    ],
    "nl": [
      "In het hart van het Ospedalebos biedt de Refuge sinds 1986 zijn Corsicaanse specialiteiten aan."
    ]
  },
  "rdfs:label": {
    "fr": [
      "Le Refuge"
    ]
  },
  "hasBeenCreatedBy": {
    "@id": "https://data.datatourisme.fr/13/84c6494d-3085-3c63-a55c-db8cb047fadd",
    "dc:identifier": "1738",
    "schema:email": [
      "camillef.omt@gmail.com",
      "direction@destination-sudcorse.com",
      "gestion@destination-sudcorse.com",
      "promotion@destination-sudcorse.com",
      "webmaster@destination-sudcorse.com"
    ],
    "schema:legalName": "Porto Vecchio Tourisme",
    "@type": [
      "schema:Organization",
      "foaf:Agent",
      "Agent"
    ],
    "foaf:homepage": [
      "http://www.ot-portovecchio.com/"
    ]
  },
  "hasBeenPublishedBy": [
    {
      "@id": "https://data.datatourisme.fr/8a9feb4b-2cbd-3d2c-b507-bd6c6776b23b",
      "schema:legalName": "Apidae Tourisme Scic SA - source : Apidae Tourisme",
      "@type": [
        "schema:Organization",
        "foaf:Agent",
        "Agent"
      ],
      "foaf:homepage": [
        "https://www.apidae-tourisme.com/"
      ]
    }
  ],
  "hasContact": [
    {
      "@id": "https://data.datatourisme.fr/e2df79f6-4e56-3eea-ac7d-81495a2d7789",
      "schema:email": [
        "lerefugefm@gmail.com"
      ],
      "schema:telephone": [
        "+33 4 95 70 00 39"
      ],
      "@type": [
        "foaf:Agent",
        "Agent"
      ],
      "foaf:homepage": [
        "http://lerefugecartalavonu.com/"
      ]
    }
  ],
  "hasDescription": [
    {
      "@id": "https://data.datatourisme.fr/42ffca51-52df-364a-9b2c-83b1aef9b67c",
      "@type": [
        "Description"
      ],
      "hasTranslatedProperty": [
        {
          "@id": "https://data.datatourisme.fr/e05d2c6e-b303-3ab4-8baa-8326dec3e170",
          "dc:contributor": [
            "https://api.deepl.com/v2/translate"
          ],
          "rdf:language": [
            "es"
          ],
          "rdf:predicate": [
            "shortDescription"
          ]
        }
      ],
      "shortDescription": {
        "de": [
          "Im Herzen des Ospedale-Waldes bietet das Refuge seit 1986 seine korsischen Spezialitäten an."
        ],
        "en": [
          "In the heart of the Ospedale forest, the Refuge has been offering its Corsican specialities since 1986."
        ],
        "it": [
          "Nel cuore della foresta dell'Ospedale, il Rifugio offre dal 1986 le sue specialità corse."
        ],
        "fr": [
          "Le Refuge vous propose ses spécialités corses depuis 1986. Ouvert tous les jours, midi et soir. Soirées chants et guitares corses tous les mardis et vendredis en haute saison. Boutique de produits corses. Gîte d'étape du Mare à Mare."
        ],
        "es": [
          "Le Refuge sirve especialidades corsas desde 1986. Abierto todos los días para almorzar y cenar. Veladas de canto y guitarra corsos todos los martes y viernes en temporada alta. Tienda de productos corsos. Gîte d'étape du Mare à Mare."
        ],
        "nl": [
          "In het hart van het Ospedalebos biedt de Refuge sinds 1986 zijn Corsicaanse specialiteiten aan."
        ]
      }
    }
  ],
  "hasTranslatedProperty": [
    {
      "@id": "https://data.datatourisme.fr/ceacc547-1e36-3348-bbd3-c8792b0f985c",
      "dc:contributor": [
        "https://api.deepl.com/v2/translate"
      ],
      "rdf:language": [
        "es"
      ],
      "rdf:predicate": [
        {
          "@id": "rdfs:comment"
        }
      ]
    }
  ],
  "isLocatedAt": [
    {
      "@id": "https://data.datatourisme.fr/2a10651e-e710-35be-bbd8-49776350b485",
      "schema:address": [
        {
          "@id": "https://data.datatourisme.fr/511dc4ff-1764-3e35-b657-3b2657ef56d2",
          "schema:addressLocality": "Porto-Vecchio",
          "schema:postalCode": "20137",
          "schema:streetAddress": [
            "D 368",
            "Forêt de l'Ospedale",
            "Lieu-dit Cartalavonu"
          ],
          "@type": [
            "schema:PostalAddress",
            "PostalAddress"
          ],
          "hasAddressCity": {
            "@id": "kb:2A247",
            "@type": [
              "City"
            ],
            "rdfs:label": {
              "en": [
                "Porto-Vecchio"
              ],
              "fr": [
                "Porto-Vecchio"
              ]
            },
            "insee": "2A247",
            "isPartOfDepartment": {
              "@id": "kb:France942A",
              "@type": [
                "Department"
              ],
              "rdfs:label": {
                "en": [
                  "Corse-du-Sud"
                ],
                "fr": [
                  "Corse-du-Sud"
                ]
              },
              "insee": "2A",
              "isPartOfRegion": {
                "@id": "kb:France94",
                "@type": [
                  "Region"
                ],
                "rdfs:label": {
                  "en": [
                    "Corse"
                  ],
                  "fr": [
                    "Corse"
                  ]
                },
                "insee": "94",
                "isPartOfCountry": {
                  "@id": "kb:France",
                  "@type": [
                    "schema:Country"
                  ],
                  "rdfs:label": {
                    "de": [
                      "Frankreich"
                    ],
                    "pt": [
                      "França"
                    ],
                    "en": [
                      "France"
                    ],
                    "it": [
                      "Francia"
                    ],
                    "fr": [
                      "France"
                    ],
                    "nl": [
                      "Frankrijk"
                    ],
                    "es": [
                      "Francia"
                    ]
                  }
                }
              }
            }
          }
        }
      ],
      "schema:geo": {
        "@id": "https://data.datatourisme.fr/203ed069-2219-3224-a172-a9bd4cec60bc",
        "schema:latitude": "41.645",
        "schema:longitude": "9.176",
        "@type": [
          "schema:GeoCoordinates"
        ]
      },
      "schema:openingHoursSpecification": [
        {
          "@id": "https://data.datatourisme.fr/baee72d8-93c1-36a0-ac5c-a524f84ca01e",
          "schema:validFrom": "2023-04-01T00:00:00",
          "schema:validThrough": "2023-11-04T23:59:59",
          "@type": [
            "schema:OpeningHoursSpecification"
          ]
        }
      ],
      "@type": [
        "schema:Place",
        "Place"
      ]
    }
  ],
  "isOwnedBy": [
    {
      "@id": "https://data.datatourisme.fr/f5f950f9-5eec-32b4-a357-2c969ccf4068",
      "schema:email": [
        "camillef.omt@gmail.com",
        "direction@destination-sudcorse.com",
        "gestion@destination-sudcorse.com",
        "promotion@destination-sudcorse.com",
        "webmaster@destination-sudcorse.com"
      ],
      "schema:legalName": "Porto Vecchio Tourisme",
      "@type": [
        "schema:Organization",
        "foaf:Agent",
        "Agent"
      ],
      "foaf:homepage": [
        "http://www.ot-portovecchio.com/"
      ]
    }
  ],
  "lastUpdate": "2023-02-15",
  "lastUpdateDatatourisme": "2023-02-16T06:39:41.865Z",
  "offers": [
    {
      "@id": "https://data.datatourisme.fr/74d45827-e293-323d-ab2e-69c7a6810f7c",
      "schema:priceSpecification": [
        {
          "@id": "https://data.datatourisme.fr/e5bd953e-f612-3d35-8985-7164e0d9bfce",
          "schema:maxPrice": [
            "30"
          ],
          "schema:minPrice": [
            "14"
          ],
          "schema:priceCurrency": "EUR",
          "@type": [
            "schema:PriceSpecification",
            "PriceSpecification"
          ],
          "appliesOnPeriod": [
            {
              "@id": "https://data.datatourisme.fr/139f5e2c-6d26-38c8-98fb-cc6481f547ed",
              "@type": [
                "Period"
              ],
              "endDate": "2023-11-04",
              "startDate": "2023-04-01"
            }
          ]
        }
      ],
      "@type": [
        "schema:Offer",
        "Offer"
      ]
    }
  ]
}